exex/parse.py
exex-1.0.0.dist-info/LICENSE
exex-1.0.0.dist-info/WHEEL
exex-1.0.0.dist-info/METADATA
exex-1.0.0.dist-info/RECORD
