Metadata-Version: 2.1
Name: exex
Version: 1.0.0
Summary: Extract data from Excel documents.
Home-page: https://github.com/vikpe/exex
License: MIT
Keywords: excel,extract,parser,xlsx
Author: Viktor Persson
Requires-Python: >=3.6.2,<4.0.0
Classifier: Development Status :: 5 - Production/Stable
Classifier: License :: OSI Approved :: MIT License
Classifier: Operating System :: MacOS :: MacOS X
Classifier: Operating System :: Microsoft :: Windows
Classifier: Operating System :: POSIX
Classifier: Programming Language :: Python
Classifier: Programming Language :: Python :: 3
Classifier: Programming Language :: Python :: 3.10
Classifier: Programming Language :: Python :: 3.6
Classifier: Programming Language :: Python :: 3.7
Classifier: Programming Language :: Python :: 3.8
Classifier: Programming Language :: Python :: 3.9
Classifier: Topic :: Office/Business :: Financial :: Spreadsheet
Classifier: Topic :: Utilities
Requires-Dist: openpyxl (>=3.0,<4.0)
Project-URL: Repository, https://github.com/vikpe/exex
